LICENSE
MANIFEST.in
README.md
pyproject.toml
setup.py
pygas/__init__.py
pygas/aligner.py
pygas/alignercpu.py
pygas/alignergpu.py
pygas/classes.py
pygas/cli.py
pygas/constants.py
pygas/main.py
pygas/matrix.c
pygas/matrix.pyx
pygas.egg-info/PKG-INFO
pygas.egg-info/SOURCES.txt
pygas.egg-info/dependency_links.txt
pygas.egg-info/entry_points.txt
pygas.egg-info/requires.txt
pygas.egg-info/top_level.txt