Metadata-Version: 2.1
Name: pygas
Version: 1.0.4
Summary: python Guide aligned Sequences
Home-page: https://github.com/cancerit/pygas
Author: Keiran M Raine
Author-email: cgphelp@sanger.ac.uk
License: AGPL-3.0
Platform: UNKNOWN
Requires-Python: >= 3.9
License-File: LICENSE
